telegram_reminder_bot/__init__.py
telegram_reminder_bot/bot.py
telegram_reminder_bot/config.example.ini
telegram_reminder_bot/config.ini
telegram_reminder_bot/entrypoint.py
telegram_reminder_bot/models.py
telegram_reminder_bot/telegram_reminder_bot.db
telegram_reminder_bot/test.db
telegram_reminder_bot-0.1.0.dist-info/entry_points.txt
telegram_reminder_bot-0.1.0.dist-info/LICENSE
telegram_reminder_bot-0.1.0.dist-info/WHEEL
telegram_reminder_bot-0.1.0.dist-info/METADATA
telegram_reminder_bot-0.1.0.dist-info/RECORD
