Metadata-Version: 2.1
Name: telegram-reminder-bot
Version: 0.1.0
Summary: A telegram bot to remind you important stuff
License: MIT
Author: Yoann Piétri
Author-email: me@nanoy.fr
Requires-Python: >=3.9,<4.0
Classifier: License :: OSI Approved :: MIT License
Classifier: Programming Language :: Python :: 3
Classifier: Programming Language :: Python :: 3.10
Classifier: Programming Language :: Python :: 3.9
Requires-Dist: SQLAlchemy (>=1.4.11,<2.0.0)
Requires-Dist: croniter (>=1.1.0,<2.0.0)
Requires-Dist: daemons[daemon] (>=1.3.2,<2.0.0)
Requires-Dist: python-dateutil (>=2.8.1,<3.0.0)
Requires-Dist: python-telegram-bot (>=13.4.1,<14.0.0)
